[
  {
    "Id": 0,
    "Route": "yulyakirill",
    "Title": "Юля и Кирилл",
    "smallPortrait": {
      "textureTag": "smallPortrait",
      "src": "https://raw.githubusercontent.com/iasvobodin/svs/images/static/image/jpg/480/20-08-29-14-42-00.jpg"
    },
    "largePortrait": {
      "textureTag": "largePortrait",
      "src": "https://raw.githubusercontent.com/iasvobodin/svs/images/static/image/jpg/720/20-08-29-14-42-00.jpg"
    },
    "smallLandscape": {
      "textureTag": "smallLandscape",
      "src": "https://raw.githubusercontent.com/iasvobodin/svs/images/static/image/jpg/480/20-08-29-16-20-24.jpg"
    },
    "largeLandscape": {
      "textureTag": "largeLandscape",
      "src": "https://raw.githubusercontent.com/iasvobodin/svs/images/static/image/jpg/720/20-08-29-16-20-24.jpg"
    },
    "LandscapeFileName": "20-08-29-16-20-24",
    "PortraitFileName": "20-08-29-14-42-00",
    "PortraitAspect": 0.667,
    "LandscapeAspect": 1.5,
    "ColorHex": "#837972",
    "ColorVector": [
      0.514,
      0.475,
      0.447
    ]
  },
  {
    "Id": 1,
    "Route": "yulyaevgeniy",
    "Title": "Юля и Евгений",
    "smallPortrait": {
      "textureTag": "smallPortrait",
      "src": "https://raw.githubusercontent.com/iasvobodin/svs/images/static/image/jpg/480/20-03-09-11-17-09.jpg"
    },
    "largePortrait": {
      "textureTag": "largePortrait",
      "src": "https://raw.githubusercontent.com/iasvobodin/svs/images/static/image/jpg/720/20-03-09-11-17-09.jpg"
    },
    "smallLandscape": {
      "textureTag": "smallLandscape",
      "src": "https://raw.githubusercontent.com/iasvobodin/svs/images/static/image/jpg/480/20-03-09-11-13-31.jpg"
    },
    "largeLandscape": {
      "textureTag": "largeLandscape",
      "src": "https://raw.githubusercontent.com/iasvobodin/svs/images/static/image/jpg/720/20-03-09-11-13-31.jpg"
    },
    "LandscapeFileName": "20-03-09-11-13-31",
    "PortraitFileName": "20-03-09-11-17-09",
    "PortraitAspect": 0.667,
    "LandscapeAspect": 1.5,
    "ColorHex": "#d8baab",
    "ColorVector": [
      0.847,
      0.7290000000000001,
      0.6709999999999999
    ]
  },
  {
    "Id": 2,
    "Route": "nastyaigor",
    "Title": "Анастасия и Игорь",
    "smallPortrait": {
      "textureTag": "smallPortrait",
      "src": "https://raw.githubusercontent.com/iasvobodin/svs/images/static/image/jpg/480/20-07-03-17-25-34.jpg"
    },
    "largePortrait": {
      "textureTag": "largePortrait",
      "src": "https://raw.githubusercontent.com/iasvobodin/svs/images/static/image/jpg/720/20-07-03-17-25-34.jpg"
    },
    "smallLandscape": {
      "textureTag": "smallLandscape",
      "src": "https://raw.githubusercontent.com/iasvobodin/svs/images/static/image/jpg/480/20-07-03-17-11-29.jpg"
    },
    "largeLandscape": {
      "textureTag": "largeLandscape",
      "src": "https://raw.githubusercontent.com/iasvobodin/svs/images/static/image/jpg/720/20-07-03-17-11-29.jpg"
    },
    "LandscapeFileName": "20-07-03-17-11-29",
    "PortraitFileName": "20-07-03-17-25-34",
    "PortraitAspect": 0.667,
    "LandscapeAspect": 1.5,
    "ColorHex": "#dde5eb",
    "ColorVector": [
      0.867,
      0.898,
      0.922
    ]
  },
  {
    "Id": 3,
    "Route": "inna",
    "Title": "Инна",
    "smallPortrait": {
      "textureTag": "smallPortrait",
      "src": "https://raw.githubusercontent.com/iasvobodin/svs/images/static/image/jpg/480/20-08-03-14-47-25.jpg"
    },
    "largePortrait": {
      "textureTag": "largePortrait",
      "src": "https://raw.githubusercontent.com/iasvobodin/svs/images/static/image/jpg/720/20-08-03-14-47-25.jpg"
    },
    "smallLandscape": {
      "textureTag": "smallLandscape",
      "src": "https://raw.githubusercontent.com/iasvobodin/svs/images/static/image/jpg/480/20-08-03-14-42-01.jpg"
    },
    "largeLandscape": {
      "textureTag": "largeLandscape",
      "src": "https://raw.githubusercontent.com/iasvobodin/svs/images/static/image/jpg/720/20-08-03-14-42-01.jpg"
    },
    "LandscapeFileName": "20-08-03-14-42-01",
    "PortraitFileName": "20-08-03-14-47-25",
    "PortraitAspect": 0.667,
    "LandscapeAspect": 1.5,
    "ColorHex": "#98836d",
    "ColorVector": [
      0.596,
      0.514,
      0.42700000000000005
    ]
  },
  {
    "Id": 4,
    "Route": "bacheloretteparty",
    "Title": "Девичник",
    "smallPortrait": {
      "textureTag": "smallPortrait",
      "src": "https://raw.githubusercontent.com/iasvobodin/svs/images/static/image/jpg/480/19-05-05-15-36-26.jpg"
    },
    "largePortrait": {
      "textureTag": "largePortrait",
      "src": "https://raw.githubusercontent.com/iasvobodin/svs/images/static/image/jpg/720/19-05-05-15-36-26.jpg"
    },
    "smallLandscape": {
      "textureTag": "smallLandscape",
      "src": "https://raw.githubusercontent.com/iasvobodin/svs/images/static/image/jpg/480/19-05-05-15-24-54.jpg"
    },
    "largeLandscape": {
      "textureTag": "largeLandscape",
      "src": "https://raw.githubusercontent.com/iasvobodin/svs/images/static/image/jpg/720/19-05-05-15-24-54.jpg"
    },
    "LandscapeFileName": "19-05-05-15-24-54",
    "PortraitFileName": "19-05-05-15-36-26",
    "PortraitAspect": 0.668,
    "LandscapeAspect": 1.498,
    "ColorHex": "#534132",
    "ColorVector": [
      0.325,
      0.255,
      0.196
    ]
  },
  {
    "Id": 5,
    "Route": "ekaterinapavel",
    "Title": "Екатерина и Павел",
    "smallPortrait": {
      "textureTag": "smallPortrait",
      "src": "https://raw.githubusercontent.com/iasvobodin/svs/images/static/image/jpg/480/19-05-01-12-13-58.jpg"
    },
    "largePortrait": {
      "textureTag": "largePortrait",
      "src": "https://raw.githubusercontent.com/iasvobodin/svs/images/static/image/jpg/720/19-05-01-12-13-58.jpg"
    },
    "smallLandscape": {
      "textureTag": "smallLandscape",
      "src": "https://raw.githubusercontent.com/iasvobodin/svs/images/static/image/jpg/480/19-05-01-12-24-16.jpg"
    },
    "largeLandscape": {
      "textureTag": "largeLandscape",
      "src": "https://raw.githubusercontent.com/iasvobodin/svs/images/static/image/jpg/720/19-05-01-12-24-16.jpg"
    },
    "LandscapeFileName": "19-05-01-12-24-16",
    "PortraitFileName": "19-05-01-12-13-58",
    "PortraitAspect": 0.668,
    "LandscapeAspect": 1.498,
    "ColorHex": "#434542",
    "ColorVector": [
      0.263,
      0.271,
      0.259
    ]
  },
  {
    "Id": 6,
    "Route": "angelinaroman",
    "Title": "Ангелина и Роман",
    "smallPortrait": {
      "textureTag": "smallPortrait",
      "src": "https://raw.githubusercontent.com/iasvobodin/svs/images/static/image/jpg/480/19-05-05-16-18-52.jpg"
    },
    "largePortrait": {
      "textureTag": "largePortrait",
      "src": "https://raw.githubusercontent.com/iasvobodin/svs/images/static/image/jpg/720/19-05-05-16-18-52.jpg"
    },
    "smallLandscape": {
      "textureTag": "smallLandscape",
      "src": "https://raw.githubusercontent.com/iasvobodin/svs/images/static/image/jpg/480/19-05-05-16-11-45.jpg"
    },
    "largeLandscape": {
      "textureTag": "largeLandscape",
      "src": "https://raw.githubusercontent.com/iasvobodin/svs/images/static/image/jpg/720/19-05-05-16-11-45.jpg"
    },
    "LandscapeFileName": "19-05-05-16-11-45",
    "PortraitFileName": "19-05-05-16-18-52",
    "PortraitAspect": 0.668,
    "LandscapeAspect": 1.498,
    "ColorHex": "#593828",
    "ColorVector": [
      0.349,
      0.22,
      0.157
    ]
  },
  {
    "Id": 7,
    "Route": "alexandravadim",
    "Title": "Александра и Вадим",
    "smallPortrait": {
      "textureTag": "smallPortrait",
      "src": "https://raw.githubusercontent.com/iasvobodin/svs/images/static/image/jpg/480/19-08-24-16-57-52.jpg"
    },
    "largePortrait": {
      "textureTag": "largePortrait",
      "src": "https://raw.githubusercontent.com/iasvobodin/svs/images/static/image/jpg/720/19-08-24-16-57-52.jpg"
    },
    "smallLandscape": {
      "textureTag": "smallLandscape",
      "src": "https://raw.githubusercontent.com/iasvobodin/svs/images/static/image/jpg/480/19-08-24-16-57-52.jpg"
    },
    "largeLandscape": {
      "textureTag": "largeLandscape",
      "src": "https://raw.githubusercontent.com/iasvobodin/svs/images/static/image/jpg/720/19-08-24-16-57-52.jpg"
    },
    "LandscapeFileName": "19-08-24-16-57-52",
    "LandscapeAspect": 1.498,
    "ColorHex": "#a48b6b",
    "ColorVector": [
      0.643,
      0.545,
      0.42
    ]
  },
  {
    "Id": 8,
    "Route": "elenanikita",
    "Title": "Лена и Никита",
    "smallPortrait": {
      "textureTag": "smallPortrait",
      "src": "https://raw.githubusercontent.com/iasvobodin/svs/images/static/image/jpg/480/19-05-10-17-21-49.jpg"
    },
    "largePortrait": {
      "textureTag": "largePortrait",
      "src": "https://raw.githubusercontent.com/iasvobodin/svs/images/static/image/jpg/720/19-05-10-17-21-49.jpg"
    },
    "smallLandscape": {
      "textureTag": "smallLandscape",
      "src": "https://raw.githubusercontent.com/iasvobodin/svs/images/static/image/jpg/480/19-05-10-17-43-45.jpg"
    },
    "largeLandscape": {
      "textureTag": "largeLandscape",
      "src": "https://raw.githubusercontent.com/iasvobodin/svs/images/static/image/jpg/720/19-05-10-17-43-45.jpg"
    },
    "LandscapeFileName": "19-05-10-17-43-45",
    "PortraitFileName": "19-05-10-17-21-49",
    "PortraitAspect": 0.668,
    "LandscapeAspect": 1.498,
    "ColorHex": "#4a4237",
    "ColorVector": [
      0.29,
      0.259,
      0.21600000000000003
    ]
  },
  {
    "Id": 9,
    "Route": "dashamaksim",
    "Title": "Даша и Максим",
    "smallPortrait": {
      "textureTag": "smallPortrait",
      "src": "https://raw.githubusercontent.com/iasvobodin/svs/images/static/image/jpg/480/19-05-07-19-38-34.jpg"
    },
    "largePortrait": {
      "textureTag": "largePortrait",
      "src": "https://raw.githubusercontent.com/iasvobodin/svs/images/static/image/jpg/720/19-05-07-19-38-34.jpg"
    },
    "smallLandscape": {
      "textureTag": "smallLandscape",
      "src": "https://raw.githubusercontent.com/iasvobodin/svs/images/static/image/jpg/480/19-05-07-19-32-56.jpg"
    },
    "largeLandscape": {
      "textureTag": "largeLandscape",
      "src": "https://raw.githubusercontent.com/iasvobodin/svs/images/static/image/jpg/720/19-05-07-19-32-56.jpg"
    },
    "LandscapeFileName": "19-05-07-19-32-56",
    "PortraitFileName": "19-05-07-19-38-34",
    "PortraitAspect": 0.668,
    "LandscapeAspect": 1.498,
    "ColorHex": "#487fab",
    "ColorVector": [
      0.282,
      0.498,
      0.6709999999999999
    ]
  },
  {
    "Id": 10,
    "Route": "alenaalexei",
    "Title": "Алёна и Алексей",
    "smallPortrait": {
      "textureTag": "smallPortrait",
      "src": "https://raw.githubusercontent.com/iasvobodin/svs/images/static/image/jpg/480/19-07-27-10-14-37.jpg"
    },
    "largePortrait": {
      "textureTag": "largePortrait",
      "src": "https://raw.githubusercontent.com/iasvobodin/svs/images/static/image/jpg/720/19-07-27-10-14-37.jpg"
    },
    "smallLandscape": {
      "textureTag": "smallLandscape",
      "src": "https://raw.githubusercontent.com/iasvobodin/svs/images/static/image/jpg/480/19-07-27-18-08-26.jpg"
    },
    "largeLandscape": {
      "textureTag": "largeLandscape",
      "src": "https://raw.githubusercontent.com/iasvobodin/svs/images/static/image/jpg/720/19-07-27-18-08-26.jpg"
    },
    "LandscapeFileName": "19-07-27-18-08-26",
    "PortraitFileName": "19-07-27-10-14-37",
    "PortraitAspect": 0.668,
    "LandscapeAspect": 1.498,
    "ColorHex": "#46242e",
    "ColorVector": [
      0.275,
      0.141,
      0.18
    ]
  },
  {
    "Id": 11,
    "Route": "ritavlad",
    "Title": "Рита и Влад",
    "smallPortrait": {
      "textureTag": "smallPortrait",
      "src": "https://raw.githubusercontent.com/iasvobodin/svs/images/static/image/jpg/480/19-06-15-10-17-30.jpg"
    },
    "largePortrait": {
      "textureTag": "largePortrait",
      "src": "https://raw.githubusercontent.com/iasvobodin/svs/images/static/image/jpg/720/19-06-15-10-17-30.jpg"
    },
    "smallLandscape": {
      "textureTag": "smallLandscape",
      "src": "https://raw.githubusercontent.com/iasvobodin/svs/images/static/image/jpg/480/19-06-15-11-55-28.jpg"
    },
    "largeLandscape": {
      "textureTag": "largeLandscape",
      "src": "https://raw.githubusercontent.com/iasvobodin/svs/images/static/image/jpg/720/19-06-15-11-55-28.jpg"
    },
    "LandscapeFileName": "19-06-15-11-55-28",
    "PortraitFileName": "19-06-15-10-17-30",
    "PortraitAspect": 0.668,
    "LandscapeAspect": 1.498,
    "ColorHex": "#4c372c",
    "ColorVector": [
      0.298,
      0.21600000000000003,
      0.17300000000000001
    ]
  },
  {
    "Id": 12,
    "Route": "irinaivan",
    "Title": "Ирина и Иван",
    "smallPortrait": {
      "textureTag": "smallPortrait",
      "src": "https://raw.githubusercontent.com/iasvobodin/svs/images/static/image/jpg/480/19-03-02-12-03-07.jpg"
    },
    "largePortrait": {
      "textureTag": "largePortrait",
      "src": "https://raw.githubusercontent.com/iasvobodin/svs/images/static/image/jpg/720/19-03-02-12-03-07.jpg"
    },
    "smallLandscape": {
      "textureTag": "smallLandscape",
      "src": "https://raw.githubusercontent.com/iasvobodin/svs/images/static/image/jpg/480/19-03-02-17-25-38.jpg"
    },
    "largeLandscape": {
      "textureTag": "largeLandscape",
      "src": "https://raw.githubusercontent.com/iasvobodin/svs/images/static/image/jpg/720/19-03-02-17-25-38.jpg"
    },
    "LandscapeFileName": "19-03-02-17-25-38",
    "PortraitFileName": "19-03-02-12-03-07",
    "PortraitAspect": 0.668,
    "LandscapeAspect": 1.498,
    "ColorHex": "#503a2c",
    "ColorVector": [
      0.314,
      0.22699999999999998,
      0.17300000000000001
    ]
  }
]