{
  "id": "18",
  "Name": "SvetaVeronika060920",
  "Title": "Света и Вероника",
  "Descripion": "",
  "Type": "portrait",
  "EngDescription": "",
  "ImageName": [
    "20-09-06-13-05-57",
    "20-09-06-13-06-02",
    "20-09-06-13-07-44",
    "20-09-06-13-10-46",
    "20-09-06-13-11-16",
    "20-09-06-13-12-55",
    "20-09-06-13-14-19",
    "20-09-06-13-16-04",
    "20-09-06-13-17-15",
    "20-09-06-13-20-30",
    "20-09-06-13-21-22",
    "20-09-06-13-22-44",
    "20-09-06-13-23-47",
    "20-09-06-13-24-20",
    "20-09-06-13-25-23",
    "20-09-06-13-25-36",
    "20-09-06-13-25-41",
    "20-09-06-13-25-44",
    "20-09-06-13-26-51",
    "20-09-06-13-27-34",
    "20-09-06-13-27-46"
  ],
  "Aspect": [
    0.667,
    0.667,
    0.667,
    1.5,
    0.667,
    1.5,
    0.667,
    0.667,
    1.5,
    0.667,
    1.5,
    0.667,
    0.667,
    0.667,
    0.667,
    0.667,
    0.667,
    0.667,
    1.5,
    0.667,
    0.667
  ],
  "Cover": {
    "Name": "20-09-06-13-21-22",
    "Params": {
      "Colors": {
        "color": [
          [
            72,
            61,
            55
          ],
          [
            207,
            182,
            168
          ],
          [
            158,
            120,
            94
          ],
          [
            178,
            185,
            191
          ],
          [
            156,
            160,
            165
          ]
        ],
        "Name": "20-09-06-13-21-22.jpg",
        "id": 770
      },
      "Color": [
        72,
        61,
        55
      ],
      "Sh": "1/200",
      "F": 4,
      "Fl": 70
    },
    "Aspect": 1.5,
    "Keywords": [
      "cover",
      "SvetaVeronika060920"
    ]
  },
  "Portrait": "20-09-06-13-27-34",
  "PortraitAspect": 0.667,
  "Spec": [
    {
      "Colors": {
        "color": [
          [
            30,
            29,
            31
          ],
          [
            199,
            185,
            181
          ],
          [
            175,
            182,
            188
          ],
          [
            147,
            152,
            161
          ],
          [
            131,
            113,
            106
          ]
        ],
        "Name": "20-09-06-13-05-57.jpg",
        "id": 760
      },
      "Color": [
        30,
        29,
        31
      ],
      "Sh": "1/200",
      "F": 4,
      "Fl": 50
    },
    {
      "Colors": {
        "color": [
          [
            29,
            29,
            29
          ],
          [
            214,
            214,
            214
          ],
          [
            140,
            140,
            140
          ],
          [
            148,
            148,
            148
          ],
          [
            132,
            132,
            132
          ]
        ],
        "Name": "20-09-06-13-06-02.jpg",
        "id": 761
      },
      "Color": [
        29,
        29,
        29
      ],
      "Sh": "1/200",
      "F": 4,
      "Fl": 55
    },
    {
      "Colors": {
        "color": [
          [
            37,
            32,
            31
          ],
          [
            197,
            187,
            183
          ],
          [
            145,
            149,
            155
          ],
          [
            122,
            127,
            135
          ],
          [
            166,
            88,
            81
          ]
        ],
        "Name": "20-09-06-13-07-44.jpg",
        "id": 762
      },
      "Color": [
        37,
        32,
        31
      ],
      "Sh": "1/200",
      "F": 4,
      "Fl": 42
    },
    {
      "Colors": {
        "color": [
          [
            196,
            165,
            149
          ],
          [
            35,
            29,
            27
          ],
          [
            139,
            97,
            76
          ],
          [
            160,
            159,
            157
          ],
          [
            140,
            132,
            140
          ]
        ],
        "Name": "20-09-06-13-10-46.jpg",
        "id": 763
      },
      "Color": [
        196,
        165,
        149
      ],
      "Sh": "1/200",
      "F": 4,
      "Fl": 70
    },
    {
      "Colors": {
        "color": [
          [
            173,
            140,
            121
          ],
          [
            26,
            22,
            23
          ],
          [
            84,
            50,
            36
          ],
          [
            181,
            183,
            189
          ],
          [
            99,
            74,
            59
          ]
        ],
        "Name": "20-09-06-13-11-16.jpg",
        "id": 764
      },
      "Color": [
        173,
        140,
        121
      ],
      "Sh": "1/200",
      "F": 4,
      "Fl": 62
    },
    {
      "Colors": {
        "color": [
          [
            206,
            170,
            153
          ],
          [
            20,
            15,
            14
          ],
          [
            148,
            151,
            153
          ],
          [
            120,
            81,
            69
          ],
          [
            128,
            130,
            136
          ]
        ],
        "Name": "20-09-06-13-12-55.jpg",
        "id": 765
      },
      "Color": [
        206,
        170,
        153
      ],
      "Sh": "1/200",
      "F": 4,
      "Fl": 62
    },
    {
      "Colors": {
        "color": [
          [
            177,
            176,
            178
          ],
          [
            27,
            25,
            29
          ],
          [
            107,
            70,
            57
          ],
          [
            111,
            119,
            127
          ],
          [
            148,
            103,
            76
          ]
        ],
        "Name": "20-09-06-13-14-19.jpg",
        "id": 766
      },
      "Color": [
        177,
        176,
        178
      ],
      "Sh": "1/200",
      "F": 4,
      "Fl": 62
    },
    {
      "Colors": {
        "color": [
          [
            60,
            57,
            56
          ],
          [
            199,
            191,
            184
          ],
          [
            138,
            142,
            143
          ],
          [
            185,
            155,
            140
          ],
          [
            156,
            167,
            176
          ]
        ],
        "Name": "20-09-06-13-16-04.jpg",
        "id": 767
      },
      "Color": [
        60,
        57,
        56
      ],
      "Sh": "1/200",
      "F": 2.8,
      "Fl": 50
    },
    {
      "Colors": {
        "color": [
          [
            229,
            229,
            229
          ],
          [
            40,
            40,
            40
          ],
          [
            151,
            151,
            151
          ],
          [
            114,
            114,
            114
          ],
          [
            140,
            140,
            140
          ]
        ],
        "Name": "20-09-06-13-17-15.jpg",
        "id": 768
      },
      "Color": [
        229,
        229,
        229
      ],
      "Sh": "1/200",
      "F": 2.8,
      "Fl": 52
    },
    {
      "Colors": {
        "color": [
          [
            189,
            188,
            190
          ],
          [
            33,
            32,
            35
          ],
          [
            98,
            82,
            77
          ],
          [
            103,
            112,
            119
          ],
          [
            155,
            112,
            81
          ]
        ],
        "Name": "20-09-06-13-20-30.jpg",
        "id": 769
      },
      "Color": [
        189,
        188,
        190
      ],
      "Sh": "1/200",
      "F": 4,
      "Fl": 58
    },
    {
      "Colors": {
        "color": [
          [
            72,
            61,
            55
          ],
          [
            207,
            182,
            168
          ],
          [
            158,
            120,
            94
          ],
          [
            178,
            185,
            191
          ],
          [
            156,
            160,
            165
          ]
        ],
        "Name": "20-09-06-13-21-22.jpg",
        "id": 770
      },
      "Color": [
        72,
        61,
        55
      ],
      "Sh": "1/200",
      "F": 4,
      "Fl": 70
    },
    {
      "Colors": {
        "color": [
          [
            175,
            175,
            175
          ],
          [
            26,
            26,
            28
          ],
          [
            100,
            103,
            105
          ],
          [
            94,
            64,
            54
          ],
          [
            137,
            96,
            68
          ]
        ],
        "Name": "20-09-06-13-22-44.jpg",
        "id": 771
      },
      "Color": [
        175,
        175,
        175
      ],
      "Sh": "1/200",
      "F": 4,
      "Fl": 38
    },
    {
      "Colors": {
        "color": [
          [
            196,
            161,
            139
          ],
          [
            24,
            23,
            24
          ],
          [
            89,
            56,
            41
          ],
          [
            132,
            87,
            55
          ],
          [
            109,
            91,
            76
          ]
        ],
        "Name": "20-09-06-13-23-47.jpg",
        "id": 772
      },
      "Color": [
        196,
        161,
        139
      ],
      "Sh": "1/200",
      "F": 4,
      "Fl": 70
    },
    {
      "Colors": {
        "color": [
          [
            210,
            172,
            149
          ],
          [
            31,
            30,
            32
          ],
          [
            130,
            92,
            69
          ],
          [
            153,
            161,
            167
          ],
          [
            135,
            136,
            142
          ]
        ],
        "Name": "20-09-06-13-24-20.jpg",
        "id": 773
      },
      "Color": [
        210,
        172,
        149
      ],
      "Sh": "1/200",
      "F": 4,
      "Fl": 55
    },
    {
      "Colors": {
        "color": [
          [
            193,
            188,
            188
          ],
          [
            45,
            42,
            43
          ],
          [
            116,
            118,
            121
          ],
          [
            110,
            68,
            51
          ],
          [
            143,
            100,
            74
          ]
        ],
        "Name": "20-09-06-13-25-23.jpg",
        "id": 774
      },
      "Color": [
        193,
        188,
        188
      ],
      "Sh": "1/200",
      "F": 4,
      "Fl": 50
    },
    {
      "Colors": {
        "color": [
          [
            199,
            185,
            180
          ],
          [
            38,
            26,
            22
          ],
          [
            112,
            67,
            50
          ],
          [
            147,
            101,
            73
          ],
          [
            123,
            119,
            120
          ]
        ],
        "Name": "20-09-06-13-25-36.jpg",
        "id": 775
      },
      "Color": [
        199,
        185,
        180
      ],
      "Sh": "1/200",
      "F": 4,
      "Fl": 70
    },
    {
      "Colors": {
        "color": [
          [
            201,
            185,
            178
          ],
          [
            36,
            23,
            18
          ],
          [
            115,
            70,
            52
          ],
          [
            144,
            100,
            74
          ],
          [
            121,
            113,
            107
          ]
        ],
        "Name": "20-09-06-13-25-41.jpg",
        "id": 776
      },
      "Color": [
        201,
        185,
        178
      ],
      "Sh": "1/200",
      "F": 4,
      "Fl": 70
    },
    {
      "Colors": {
        "color": [
          [
            38,
            33,
            32
          ],
          [
            217,
            186,
            170
          ],
          [
            105,
            63,
            46
          ],
          [
            149,
            99,
            68
          ],
          [
            121,
            119,
            119
          ]
        ],
        "Name": "20-09-06-13-25-44.jpg",
        "id": 777
      },
      "Color": [
        38,
        33,
        32
      ],
      "Sh": "1/200",
      "F": 4,
      "Fl": 70
    },
    {
      "Colors": {
        "color": [
          [
            215,
            191,
            179
          ],
          [
            64,
            39,
            30
          ],
          [
            119,
            70,
            50
          ],
          [
            149,
            101,
            68
          ],
          [
            176,
            129,
            101
          ]
        ],
        "Name": "20-09-06-13-26-51.jpg",
        "id": 778
      },
      "Color": [
        215,
        191,
        179
      ],
      "Sh": "1/200",
      "F": 4,
      "Fl": 62
    },
    {
      "Colors": {
        "color": [
          [
            205,
            197,
            194
          ],
          [
            33,
            28,
            29
          ],
          [
            121,
            76,
            59
          ],
          [
            159,
            112,
            83
          ],
          [
            132,
            120,
            113
          ]
        ],
        "Name": "20-09-06-13-27-34.jpg",
        "id": 779
      },
      "Color": [
        205,
        197,
        194
      ],
      "Sh": "1/200",
      "F": 4,
      "Fl": 70
    },
    {
      "Colors": {
        "color": [
          [
            201,
            185,
            176
          ],
          [
            25,
            21,
            21
          ],
          [
            112,
            70,
            48
          ],
          [
            148,
            104,
            72
          ],
          [
            121,
            117,
            113
          ]
        ],
        "Name": "20-09-06-13-27-46.jpg",
        "id": 780
      },
      "Color": [
        201,
        185,
        176
      ],
      "Sh": "1/200",
      "F": 4,
      "Fl": 70
    }
  ]
}